vnquant/__init__.py
vnquant/__version__.py
vnquant/configs/__init__.py
vnquant/configs/configs.py
vnquant/data/__init__.py
vnquant/data/dataloader.py
vnquant/data/finance.py
vnquant/data/loader/__init__.py
vnquant/data/loader/cafe.py
vnquant/data/loader/proto.py
vnquant/data/loader/vnd.py
vnquant/log/__init__.py
vnquant/log/logging.py
vnquant/plot/__init__.py
vnquant/plot/plot.py
vnquant/utils/__init__.py
vnquant/utils/exceptions.py
vnquant/utils/utils.py
vnquant-0.1.23.dist-info/METADATA
vnquant-0.1.23.dist-info/WHEEL
vnquant-0.1.23.dist-info/top_level.txt
vnquant-0.1.23.dist-info/RECORD
