Metadata-Version: 2.4
Name: vnquant
Version: 0.1.23
Summary: Viet Nam stock market
Author-email: KhanhPhamDinh <phamdinhkhanh.tkt53.neu@gmail.com>
License-Expression: MIT
Project-URL: Homepage, https://github.com/phamdinhkhanh/vnquant
Project-URL: Download, https://github.com/phamdinhkhanh/vnquant
Keywords: data,finance,stock,vietnam
Classifier: Development Status :: 3 - Alpha
Classifier: Environment :: Console
Classifier: Intended Audience :: Science/Research
Classifier: Operating System :: OS Independent
Classifier: Programming Language :: Python
Classifier: Programming Language :: Python :: 3
Classifier: Programming Language :: Python :: 3.10
Classifier: Programming Language :: Python :: 3.11
Classifier: Programming Language :: Python :: 3.12
Classifier: Topic :: Office/Business :: Financial
Requires-Python: >=3.10
Requires-Dist: bs4>=0.0.1
Requires-Dist: lxml>=4.3.0
Requires-Dist: matplotlib>=3.0.0
Requires-Dist: numpy>=1.20.2
Requires-Dist: pandas>=0.19.2
Requires-Dist: plotly>=4.2.1
Requires-Dist: pypandoc>=1.4
Requires-Dist: requests>=2.3.0
Requires-Dist: wrapt>=1.10.0
